fxlog/__init__.py
fxlog/examples.py
fxlog/fxlogger.py
fxlog/images/icons/fxlog_logo_background_dark.svg
fxlog/images/icons/fxlog_logo_background_light.svg
fxlog-0.1.1.dist-info/LICENSE
fxlog-0.1.1.dist-info/METADATA
fxlog-0.1.1.dist-info/WHEEL
fxlog-0.1.1.dist-info/top_level.txt
fxlog-0.1.1.dist-info/RECORD
