Metadata-Version: 2.1
Name: fxlog
Version: 0.1.1
Summary: A custom logging module for Python that supports colorized output and log file rotation. Includes features such as configurable log levels, custom formatters, and automatic deletion of old log files.
Home-page: https://github.com/healkeiser/fxlog
Author: Valentin Beaumont
Author-email: valentin.onze@gmail.com
License: MIT
Project-URL: Documentation, https://healkeiser.github.io/fxlog
Project-URL: GitHub, https://github.com/healkeiser/fxlog
Project-URL: Changelog, https://github.com/healkeiser/fxlog/blob/main/CHANGELOG.md
Project-URL: Source, https://github.com/healkeiser/fxlog
Project-URL: Funding, https://github.com/sponsors/healkeiser
License-File: LICENSE
Requires-Dist: colorama
